bpl/__init__.py
bpl/base.py
bpl/device.py
bpl/neurons.py
bpl/runner.py
bpl/synapses.py
bpl/utils.py
bpl/core/__init__.py
bpl/core/base.py
bpl/core/networks.py
bpl/core/neurons.py
bpl/core/neurons_base.py
bpl/core/runner.py
bpl/core/synapses.py
bpl/respa/__init__.py
bpl/respa/optimizer.py
bpl/respa/res_manager.py
brainpy_largescale-0.1.2.dist-info/LICENSE
brainpy_largescale-0.1.2.dist-info/METADATA
brainpy_largescale-0.1.2.dist-info/WHEEL
brainpy_largescale-0.1.2.dist-info/top_level.txt
brainpy_largescale-0.1.2.dist-info/RECORD
