Metadata-Version: 2.1
Name: brainpy-largescale
Version: 0.1.2
Summary: brainpy-largescale depends on brainpy
Home-page: https://github.com/NH-NCL/brainpy-largescale
Author: NanHu Neuromorphic Computing Laboratory Team
Author-email: nhnao@cnaeit.com
License: Apache-2.0 license
Project-URL: Bug Tracker, https://github.com/NH-NCL/brainpy-largescale/issues
Project-URL: Documentation, https://brainpy.readthedocs.io/
Project-URL: Source Code, https://github.com/NH-NCL/brainpy-largescale
Keywords: brainpy largescale,computational neuroscience,brain-inspired computation,dynamical systems,differential equations,brain modeling,brain dynamics modeling,brain dynamics programming
Classifier: Natural Language :: English
Classifier: Operating System :: OS Independent
Classifier: Programming Language :: Python
Classifier: Programming Language :: Python :: 3
Classifier: Programming Language :: Python :: 3.7
Classifier: Programming Language :: Python :: 3.8
Classifier: Programming Language :: Python :: 3.9
Classifier: Programming Language :: Python :: 3.10
Classifier: Intended Audience :: Science/Research
Classifier: License :: OSI Approved :: Apache Software License
Classifier: Topic :: Scientific/Engineering :: Bio-Informatics
Classifier: Topic :: Scientific/Engineering :: Mathematics
Classifier: Topic :: Scientific/Engineering :: Artificial Intelligence
Classifier: Topic :: Software Development :: Libraries
Requires-Python: >=3.7
License-File: LICENSE
Requires-Dist: numpy (>=1.15)
Requires-Dist: tqdm
Requires-Dist: brainpy (==2.2.4.0)
Requires-Dist: numba
Requires-Dist: mpi4py (==3.1.4)
Requires-Dist: mpi4jax (==0.3.11)
Requires-Dist: jax (==0.3.25)
Requires-Dist: jaxlib (==0.3.25)
Requires-Dist: matplotlib
